<?xml version="1.0" encoding="UTF-8"?>
<INVENTORY>
<ITEM>
<ITEMTYPE>P</ITEMTYPE>
<ITEMID>3022</ITEMID>
<COLOR>5</COLOR>
<MINQTY>10</MINQTY>
<NOTIFY>N</NOTIFY>
</ITEM>
<ITEM>
<ITEMTYPE>P</ITEMTYPE>
<ITEMID>4073</ITEMID>
<COLOR>34</COLOR>
<MINQTY>1</MINQTY>
<NOTIFY>N</NOTIFY>
</ITEM>
<ITEM>
<ITEMTYPE>P</ITEMTYPE>
<ITEMID>3068b</ITEMID>
<COLOR>5</COLOR>
<MINQTY>5</MINQTY>
<NOTIFY>N</NOTIFY>
</ITEM>
<ITEM>
<ITEMTYPE>P</ITEMTYPE>
<ITEMID>x127c11</ITEMID>
<COLOR>11</COLOR>
<MINQTY>1</MINQTY>
<NOTIFY>N</NOTIFY>
</ITEM>
<ITEM>
<ITEMTYPE>P</ITEMTYPE>
<ITEMID>3900</ITEMID>
<COLOR>86</COLOR>
<MINQTY>1</MINQTY>
<NOTIFY>N</NOTIFY>
</ITEM>
<ITEM>
<ITEMTYPE>P</ITEMTYPE>
<ITEMID>15712</ITEMID>
<COLOR>5</COLOR>
<MINQTY>1</MINQTY>
<NOTIFY>N</NOTIFY>
</ITEM>
</INVENTORY>
